Metadata-Version: 2.0
Name: manta-maastricht
Version: 1.2.1.2
Summary: manta_maastricht
Home-page: http://www.jordiheijman.net/
Author: UNKNOWN
Author-email: UNKNOWN
License: UNKNOWN
Platform: UNKNOWN
Requires-Dist: myokit
